plank/app/__init__.py
plank/decorator/__init__.py
plank/decorator/action.py
plank/decorator/timing.py
plank/decorator/version.py
plank/descriptor/__init__.py
plank/descriptor/action.py
plank/plugin/__init__.py
plank/plugin/asset/__init__.py
plank/plugin/module.py
plank/resource/template.toml
plank/server/__init__.py
plank/server/action/__init__.py
plank/server/action/serving.py
plank/server/action/wrapper.py
plank/server/connector/__init__.py
plank/server/connector/inline.py
plank/server/inline.py
plank/server/message/__init__.py
plank/serving/__init__.py
plank/serving/interface.py
plank/serving/service.py
plank/utils/__init__.py
plank/utils/command/__init__.py
plank/utils/command/base.py
plank/utils/error.py
plank/utils/path.py
plank-0.1.0.dist-info/entry_points.txt
plank-0.1.0.dist-info/WHEEL
plank-0.1.0.dist-info/METADATA
plank-0.1.0.dist-info/RECORD
